bodoTK/__init__.py
bodoTK/tokenize.py
bodoTK-1.2.dist-info/LICENSE
bodoTK-1.2.dist-info/METADATA
bodoTK-1.2.dist-info/WHEEL
bodoTK-1.2.dist-info/top_level.txt
bodoTK-1.2.dist-info/RECORD
